litebook-0.0.0.dist-info/METADATA
litebook-0.0.0.dist-info/WHEEL
litebook-0.0.0.dist-info/licenses/LICENSE
litebook/__init__.py
litebook/__init__.pyi
litebook/py.typed
litebook/litebook.cpython-311-darwin.so
litebook-0.0.0.dist-info/RECORD
