Metadata-Version: 2.4
Name: litebook
Version: 0.0.0
License-File: LICENSE
Summary: A pure-Python limit order book with tick sizes, market depth and visualization.
Keywords: limit order book,order book
License: MIT License
Requires-Python: >=3.11
Project-URL: repository, https://github.com/pnxenopoulos/litebook
